pythonfofa/__init__.py
pythonfofa/client.py
pythonfofa/operation.py
pythonfofa-1.0.8.dist-info/LICENSE
pythonfofa-1.0.8.dist-info/LICENSE.txt
pythonfofa-1.0.8.dist-info/METADATA
pythonfofa-1.0.8.dist-info/WHEEL
pythonfofa-1.0.8.dist-info/top_level.txt
pythonfofa-1.0.8.dist-info/RECORD
