Metadata-Version: 2.1
Name: pythonfofa
Version: 1.0.8
Summary: FOFA.info Python SDK
Home-page: https://github.com/Moxin1044/pythonfofa
Author: Moxin
Author-email: 1044631097@qq.com
License: MIT License
License-File: LICENSE
License-File: LICENSE.txt
Requires-Dist: requests
